rustc_codegen_cranelift_pre_t_x64_win_msvc_nightly_p1/__init__.py
rustc_codegen_cranelift_pre_t_x64_win_msvc_nightly_p1/data/LICENSE-APACHE
rustc_codegen_cranelift_pre_t_x64_win_msvc_nightly_p1/data/LICENSE-MIT
rustc_codegen_cranelift_pre_t_x64_win_msvc_nightly_p1/data/Readme.md
rustc_codegen_cranelift_pre_t_x64_win_msvc_nightly_p1/data/builder-config
rustc_codegen_cranelift_pre_t_x64_win_msvc_nightly_p1/data/components
rustc_codegen_cranelift_pre_t_x64_win_msvc_nightly_p1/data/git-commit-hash
rustc_codegen_cranelift_pre_t_x64_win_msvc_nightly_p1/data/git-commit-info
rustc_codegen_cranelift_pre_t_x64_win_msvc_nightly_p1/data/install.sh
rustc_codegen_cranelift_pre_t_x64_win_msvc_nightly_p1/data/rust-installer-version
rustc_codegen_cranelift_pre_t_x64_win_msvc_nightly_p1/data/version
rustc_codegen_cranelift_pre_t_x64_win_msvc_nightly_p1/data/rustc-codegen-cranelift-preview/manifest.in
rustc_codegen_cranelift_pre_t_x64_win_msvc_nightly_p1/data/rustc-codegen-cranelift-preview/lib/rustlib/x86_64-pc-windows-msvc/codegen-backends/rustc_codegen_cranelift-1.91.0-nightly.dll
rustc_codegen_cranelift_pre_t_x64_win_msvc_nightly_p1/data/rustc-codegen-cranelift-preview/lib/rustlib/x86_64-pc-windows-msvc/codegen-backends/rustc_codegen_cranelift-1.91.0-nightly.pdb
rustc_codegen_cranelift_pre_t_x64_win_msvc_nightly_p1/data/rustc-codegen-cranelift-preview/share/doc/rustc_codegen_cranelift/LICENSE-APACHE
rustc_codegen_cranelift_pre_t_x64_win_msvc_nightly_p1/data/rustc-codegen-cranelift-preview/share/doc/rustc_codegen_cranelift/LICENSE-MIT
rustc_codegen_cranelift_pre_t_x64_win_msvc_nightly_p1/data/rustc-codegen-cranelift-preview/share/doc/rustc_codegen_cranelift/Readme.md
rustc_codegen_cranelift_pre_t_x64_win_msvc_nightly_p1-1.91.0.dist-info/METADATA
rustc_codegen_cranelift_pre_t_x64_win_msvc_nightly_p1-1.91.0.dist-info/WHEEL
rustc_codegen_cranelift_pre_t_x64_win_msvc_nightly_p1-1.91.0.dist-info/top_level.txt
rustc_codegen_cranelift_pre_t_x64_win_msvc_nightly_p1-1.91.0.dist-info/RECORD
