Metadata-Version: 2.4
Name: rustc_codegen_cranelift_pre_t_x64_win_msvc_nightly_p1
Version: 1.91.0
Summary: Segment rustc-codegen-cranelift-preview.target.x86_64-pc-windows-msvc part p1
License: MIT
